[
    {
        "title": "Inesis Kids golf short-sleeved polo shirt MW500 red",
        "original_price": "₹199",
        "mrp": "₹1,399",
        "ratingcount": "146",
        "rating": "4.0",
        "discount": "85% off",
        "url": "https://www.decathlon.in/p/8560088/kids-golf-short-sleeved-polo-shirt-mw500-red",
        "imageurl": "https://contents.mediadecathlon.com/p2130976/1c0bf8cd4404d8151c78a4d21b62dcc5/kids-golf-short-sleeved-polo-shirt-mw500-red.jpg?format=auto&quality=70&f=320x0"
    },
    {
        "title": "Domyos Kid's Multisports Cotton T-Shirt 100 - Cotton White",
        "original_price": "₹199",
        "mrp": "₹299",
        "ratingcount": "1.9k",
        "rating": "4.0",
        "discount": null,
        "url": "https://www.decathlon.in/p/8619456/kid-s-multisports-cotton-t-shirt-100-cotton-white",
        "imageurl": "https://contents.mediadecathlon.com/p2827573/e43f7134d0e70fe43d18711cf901cbb7/kid-s-multisports-cotton-t-shirt-100-cotton-white.jpg?format=auto&quality=70&f=320x0"
    },
    {
        "title": "Tarmak Kids' Basketball T-Shirt/Jersey TS500 Fast - Red",
        "original_price": "₹599",
        "mrp": "₹799",
        "ratingcount": "801",
        "rating": "4.0",
        "discount": null,
        "url": "https://www.decathlon.in/p/8773778/kids-basketball-t-shirt-jersey-ts500-fast-red",
        "imageurl": "https://contents.mediadecathlon.com/p2421686/91d81f2dedafb0ed90fdbfa34a5b71fb/kids-basketball-t-shirt-jersey-ts500-fast-red.jpg?format=auto&quality=70&f=320x0"
    },
    {
        "title": "Domyos Kids' Unisex Multisports Cotton T-Shirt - Blue",
        "original_price": "₹199",
        "mrp": "₹799",
        "ratingcount": "1.4k",
        "rating": "4.0",
        "discount": "75% off",
        "url": "https://www.decathlon.in/p/8751825/kids-unisex-multisports-cotton-t-shirt-blue",
        "imageurl": "https://contents.mediadecathlon.com/p2722633/87803f9af94d7ea55f7a76adad721bc0/kids-unisex-multisports-cotton-t-shirt-blue.jpg?format=auto&quality=70&f=320x0"
    },
    {
        "title": "Domyos Kids' Basic T-Shirt - White",
        "original_price": "₹149",
        "mrp": "",
        "ratingcount": "3.0k",
        "rating": "4.0",
        "discount": null,
        "url": "https://www.decathlon.in/p/8516223/kids-basic-t-shirt-white",
        "imageurl": "https://contents.mediadecathlon.com/p2174104/b1e9e507d94d8c4cf60027a306b531fa/kids-basic-t-shirt-white.jpg?format=auto&quality=70&f=320x0"
    },
    {
        "title": "Quechua Kids' 3-in-1 Jacket with Inner Padded Jacket MH500 7-15 Years -  Blue",
        "original_price": "₹4,999",
        "mrp": "₹6,499",
        "ratingcount": "180",
        "rating": "4.0",
        "discount": null,
        "url": "https://www.decathlon.in/p/8807327/kids-3-in-1-jacket-with-inner-padded-jacket-mh500-7-15-years-blue",
        "imageurl": "https://contents.mediadecathlon.com/p2727134/c84e83a7360b93f7405d412e0611371d/kids-3-in-1-jacket-with-inner-padded-jacket-mh500-7-15-years-blue.jpg?format=auto&quality=70&f=320x0"
    },
    {
        "title": "Kipsta Kids Football Jersey Shirt Essential - Blue",
        "original_price": "₹299",
        "mrp": "₹549",
        "ratingcount": "1.9k",
        "rating": "4.0",
        "discount": null,
        "url": "https://www.decathlon.in/p/8817147/kids-football-jersey-shirt-essential-blue",
        "imageurl": "https://contents.mediadecathlon.com/p2960270/3d9c4e10322b6136638bcffb0a8efd4c/kids-football-jersey-shirt-essential-blue.jpg?format=auto&quality=70&f=320x0"
    },
    {
        "title": "Decathlon Kids' Unisex Plain Synthetic T-Shirt - Black",
        "original_price": "₹399",
        "mrp": "₹549",
        "ratingcount": "60",
        "rating": "4.0",
        "discount": null,
        "url": "https://www.decathlon.in/p/8965428/kids-unisex-plain-synthetic-t-shirt-black",
        "imageurl": "https://contents.mediadecathlon.com/p3117454/a6f5ab5e6a2cfd549c00bfa1ed4907cb/kids-unisex-plain-synthetic-t-shirt-black.jpg?format=auto&quality=70&f=320x0"
    },
    {
        "title": "Quechua Kids’ hiking T-shirt, NH100 7-15 years - Twin Orange",
        "original_price": "₹499",
        "mrp": "₹649",
        "ratingcount": "222",
        "rating": "4.0",
        "discount": null,
        "url": "https://www.decathlon.in/p/8969266/kids-hiking-t-shirt-nh100-7-15-years-twin-orange",
        "imageurl": "https://contents.mediadecathlon.com/p3078480/437220a0728a2feaa8380438124974fd/kids-hiking-t-shirt-nh100-7-15-years-twin-orange.jpg?format=auto&quality=70&f=320x0"
    },
    {
        "title": "Kuikma Girls Tennis T-Shirt - TTS500 Pale Peach",
        "original_price": "₹599",
        "mrp": "₹899",
        "ratingcount": "497",
        "rating": "4.0",
        "discount": null,
        "url": "https://www.decathlon.in/p/8582861/girls-tennis-t-shirt-tts500-pale-peach",
        "imageurl": "https://contents.mediadecathlon.com/p2219495/bd1b47fd94eee986a21ff24f20be8fcb/girls-tennis-t-shirt-tts500-pale-peach.jpg?format=auto&quality=70&f=320x0"
    },
    {
        "title": "Domyos Kids' Baby Gym Lightweight Breathable T-Shirt - Blue",
        "original_price": "₹499",
        "mrp": "₹649",
        "ratingcount": "569",
        "rating": "4.0",
        "discount": null,
        "url": "https://www.decathlon.in/p/8853099/kids-baby-gym-lightweight-breathable-t-shirt-blue",
        "imageurl": "https://contents.mediadecathlon.com/p2827623/5596d9516e4f272a7c535848f7aca3b4/kids-baby-gym-lightweight-breathable-t-shirt-blue.jpg?format=auto&quality=70&f=320x0"
    },
    {
        "title": "Quechua Kids’ waterproof hiking jacket, MH500 7-15 years - Twin Grey",
        "original_price": "₹1,999",
        "mrp": "₹2,599",
        "ratingcount": "1.4k",
        "rating": "4.0",
        "discount": null,
        "url": "https://www.decathlon.in/p/8969459/kids-waterproof-hiking-jacket-mh500-7-15-years-twin-grey",
        "imageurl": "https://contents.mediadecathlon.com/p3078487/6a6b9df9717f6f9cb5a76364ac801e13/kids-waterproof-hiking-jacket-mh500-7-15-years-twin-grey.jpg?format=auto&quality=70&f=320x0"
    },
    {
        "title": "Kuikma Girls' Tennis T-Shirt TTS Soft - Purple",
        "original_price": "₹599",
        "mrp": "₹799",
        "ratingcount": "496",
        "rating": "4.0",
        "discount": null,
        "url": "https://www.decathlon.in/p/8968228/girls-tennis-t-shirt-tts-soft-purple",
        "imageurl": "https://contents.mediadecathlon.com/p3023885/fb5db584f55ee186aaf6f203d481f505/girls-tennis-t-shirt-tts-soft-purple.jpg?format=auto&quality=70&f=320x0"
    },
    {
        "title": "Quechua Kids’ waterproof hiking jacket, half-zip, 7-15 years, MH100 - Black",
        "original_price": "₹699",
        "mrp": "₹999",
        "ratingcount": "349",
        "rating": "4.0",
        "discount": null,
        "url": "https://www.decathlon.in/p/8797255/kids-waterproof-hiking-jacket-half-zip-7-15-years-mh100-black",
        "imageurl": "https://contents.mediadecathlon.com/p2627371/6b97be451db0669f9304c948ca2753f4/kids-waterproof-hiking-jacket-half-zip-7-15-years-mh100-black.jpg?format=auto&quality=70&f=320x0"
    },
    {
        "title": "Domyos Kid's Lightweight Breathable T-Shirt 500 - Sorbet Green",
        "original_price": "₹499",
        "mrp": "₹799",
        "ratingcount": "569",
        "rating": "4.0",
        "discount": null,
        "url": "https://www.decathlon.in/p/8906829/kid-s-lightweight-breathable-t-shirt-500-sorbet-green",
        "imageurl": "https://contents.mediadecathlon.com/p2827827/7e5087e6271eefd7f5d9a68453e7c337/kid-s-lightweight-breathable-t-shirt-500-sorbet-green.jpg?format=auto&quality=70&f=320x0"
    },
    {
        "title": "Quechua Kids’ warm hiking jacket MH100 - 7-15 years Half zip - Navy Blue",
        "original_price": "₹499",
        "mrp": "₹649",
        "ratingcount": "4.9k",
        "rating": "4.0",
        "discount": null,
        "url": "https://www.decathlon.in/p/8944989/kids-warm-hiking-jacket-mh100-7-15-years-half-zip-navy-blue",
        "imageurl": "https://contents.mediadecathlon.com/p2941474/3896a8d56920575f690ff39a47932165/kids-warm-hiking-jacket-mh100-7-15-years-half-zip-navy-blue.jpg?format=auto&quality=70&f=320x0"
    },
    {
        "title": "Decathlon Girls' Breathable Multisport T-Shirt - Pink",
        "original_price": "₹499",
        "mrp": "₹649",
        "ratingcount": "2.1k",
        "rating": "4.0",
        "discount": null,
        "url": "https://www.decathlon.in/p/8906882/girls-breathable-multisport-t-shirt-pink",
        "imageurl": "https://contents.mediadecathlon.com/p2795559/702cbe51d4bebb9438ddfea2a0a3498b/girls-breathable-multisport-t-shirt-pink.jpg?format=auto&quality=70&f=320x0"
    },
    {
        "title": "Decathlon Kids' Technical T-Shirt - Cherry Red",
        "original_price": "₹199",
        "mrp": "₹899",
        "ratingcount": "95",
        "rating": "4.0",
        "discount": "77% off",
        "url": "https://www.decathlon.in/p/8853140/kids-technical-t-shirt-cherry-red",
        "imageurl": "https://contents.mediadecathlon.com/p2729830/40858518162a2b0baf92d9d143aab6b0/kids-technical-t-shirt-cherry-red.jpg?format=auto&quality=70&f=320x0"
    },
    {
        "title": "Quechua Kids’ warm hiking jacket MH100 Half Zip - 2-6 years - Navy Blue",
        "original_price": "₹499",
        "mrp": "₹649",
        "ratingcount": "1.2k",
        "rating": "4.0",
        "discount": null,
        "url": "https://www.decathlon.in/p/8944956/kids-warm-hiking-jacket-mh100-half-zip-2-6-years-navy-blue",
        "imageurl": "https://contents.mediadecathlon.com/p2941726/adcf7590ae85d7b8f6bc3d11ead2268d/kids-warm-hiking-jacket-mh100-half-zip-2-6-years-navy-blue.jpg?format=auto&quality=70&f=320x0"
    },
    {
        "title": "Kuikma T-SHIRT LITE 560 JR ROSEWOOD PINK",
        "original_price": "₹699",
        "mrp": "₹1,049",
        "ratingcount": "1.1k",
        "rating": "4.0",
        "discount": "33% off",
        "url": "https://www.decathlon.in/p/8970533/t-shirt-lite-560-jr-rosewood-pink",
        "imageurl": "https://contents.mediadecathlon.com/p3029711/74ddbb3e388c8e0ebc51ca5d7dbe9cf5/t-shirt-lite-560-jr-rosewood-pink.jpg?format=auto&quality=70&f=320x0"
    }
]